pubg_python/__init__.py
pubg_python/base.py
pubg_python/clients.py
pubg_python/decorators.py
pubg_python/exceptions.py
pubg_python/mixins.py
pubg_python/querysets.py
pubg_python/domain/__init__.py
pubg_python/domain/base.py
pubg_python/domain/telemetry/__init__.py
pubg_python/domain/telemetry/base.py
pubg_python/domain/telemetry/data.py
pubg_python/domain/telemetry/events.py
pubg_python/domain/telemetry/objects.py
pubg_python/domain/telemetry/resources.py
back_pubg_python-0.5.2.dist-info/AUTHORS
back_pubg_python-0.5.2.dist-info/LICENSE
back_pubg_python-0.5.2.dist-info/METADATA
back_pubg_python-0.5.2.dist-info/WHEEL
back_pubg_python-0.5.2.dist-info/top_level.txt
back_pubg_python-0.5.2.dist-info/RECORD
