Metadata-Version: 2.1
Name: back-pubg-python
Version: 0.5.2
Summary: A python wrapper for the PUBG developer API
Home-page: https://github.com/ramonsaraiva/pubg-python
Author: Ramon Saraiva
Author-email: ramonsaraiva@gmail.com
License: MIT
Platform: UNKNOWN
Classifier: Development Status :: 3 - Alpha
Classifier: License :: OSI Approved :: MIT License
Classifier: Natural Language :: English
Classifier: Operating System :: OS Independent
Classifier: Programming Language :: Python :: 3
Classifier: Programming Language :: Python :: 3.6
Classifier: Topic :: Utilities
Requires-Dist: requests (>=2.18.4)
Requires-Dist: furl (>=1.0.1)
Requires-Dist: enum34 (>=1.1.6) ; python_version<='3.4'
